xpln/__init__.py
xpln/cli.py
xpln/decorators.py
xpln/google_genai.py
xpln/utils.py
xpln2me-1.0.2.dist-info/LICENSE
xpln2me-1.0.2.dist-info/METADATA
xpln2me-1.0.2.dist-info/WHEEL
xpln2me-1.0.2.dist-info/entry_points.txt
xpln2me-1.0.2.dist-info/RECORD
